experiment1edge/__init__.py
experiment1edge/cli.py
experiment1edge/image_utils.py
experiment1edge-0.1.0.dist-info/METADATA
experiment1edge-0.1.0.dist-info/WHEEL
experiment1edge-0.1.0.dist-info/entry_points.txt
experiment1edge-0.1.0.dist-info/top_level.txt
experiment1edge-0.1.0.dist-info/RECORD
